LICENSE
MANIFEST.in
README.md
setup.py
./requirements.txt
kot_update/__init__.py
kot_update/kot_update.py
kot_update.egg-info/PKG-INFO
kot_update.egg-info/SOURCES.txt
kot_update.egg-info/dependency_links.txt
kot_update.egg-info/not-zip-safe
kot_update.egg-info/requires.txt
kot_update.egg-info/top_level.txt