Metadata-Version: 2.1
Name: kot-update
Version: 0.1.0
Summary: The cloud updating system for your python applications !
Home-page: https://github.com/KOT-database/KOT-Update
License: MIT
Platform: UNKNOWN
Requires-Python: >= 3
